nonebot_plugin_lynchpined/__init__.py
nonebot_plugin_lynchpined/config.py
nonebot_plugin_lynchpined-0.1.5.dist-info/LICENSE
nonebot_plugin_lynchpined-0.1.5.dist-info/METADATA
nonebot_plugin_lynchpined-0.1.5.dist-info/WHEEL
nonebot_plugin_lynchpined-0.1.5.dist-info/RECORD
