Metadata-Version: 2.1
Name: nonebot-plugin-lynchpined
Version: 0.1.5
Summary: A nonebot2 plugin to check Lynchpin progress.
License: MIT
Author: Nightsky
Author-email: 050644zf@outlook.com
Requires-Python: >=3.8,<4.0
Classifier: License :: OSI Approved :: MIT License
Classifier: Programming Language :: Python :: 3
Classifier: Programming Language :: Python :: 3.8
Classifier: Programming Language :: Python :: 3.9
Classifier: Programming Language :: Python :: 3.10
Classifier: Programming Language :: Python :: 3.11
Classifier: Programming Language :: Python :: 3.12
Classifier: Programming Language :: Python :: 3.13
Requires-Dist: aiohttp (>=3.10.2,<4.0.0)
Requires-Dist: nonebot-plugin-apscheduler (>=0.4.0,<0.5.0)
